zerodai/Zerodai.py
zerodai/__init__.py
zerodai/ctx.py
zerodai/funcs.py
zerodai-0.0.0.14.dist-info/METADATA
zerodai-0.0.0.14.dist-info/WHEEL
zerodai-0.0.0.14.dist-info/top_level.txt
zerodai-0.0.0.14.dist-info/RECORD
